{
  "timestamp": "2025-07-29T20:32:05.494836",
  "configuration": {
    "capacity_kWh": 8000.0,
    "power_kW": 2000.0,
    "min_soc_kWh": 400.0,
    "max_soc_kWh": 7600.0,
    "initial_soc_kWh": 2400.0
  },
  "original_schedule": {
    "soc_range": "1170.7 - 4740.0 kWh",
    "violations": 0,
    "needed_fixing": false
  },
  "results": {
    "strategies_evaluated": 584,
    "strategies_implemented": 135,
    "strategies_skipped": 449,
    "total_profit": 10470.16,
    "final_soc_range": "400.0 - 7600.0 kWh",
    "total_cycles": 136.14167281250002
  },
  "skip_reasons": {
    "Flexband constraint": 309,
    "SoC": 72,
    "Time overlap": 68
  }
}